LICENSE
MANIFEST.in
README.md
requirements.txt
setup.py
lib/GenIPs.py
lib/PortRange.py
lib/__init__.py
lib/test_config.py
test_cases/TExceptions.py
test_cases/__init__.py
test_cases/early_cancel.py
test_cases/early_cancel_lost100.py
test_cases/reinv_adelay.py
test_cases/reinv_bad_ack.py
test_cases/reinv_brkn1.py
test_cases/reinv_brkn2.py
test_cases/reinv_fail.py
test_cases/reinv_frombob.py
test_cases/reinv_onhold.py
test_cases/reinvite.py
test_cases/t1.py
test_cases/t10.py
test_cases/t11.py
test_cases/t12.py
test_cases/t13.py
test_cases/t14.py
test_cases/t2.py
test_cases/t3.py
test_cases/t4.py
test_cases/t5.py
test_cases/t6.py
test_cases/t7.py
test_cases/t8.py
test_cases/t9.py
voiptests.egg-info/PKG-INFO
voiptests.egg-info/SOURCES.txt
voiptests.egg-info/dependency_links.txt
voiptests.egg-info/entry_points.txt
voiptests.egg-info/requires.txt
voiptests.egg-info/top_level.txt