Metadata-Version: 2.1
Name: voiptests
Version: 1.0.0
Summary: VoIP Integrated Tests Suite
Home-page: https://github.com/sippy/voiptests/
Author: Sippy Software, Inc.
Author-email: sobomax@sippysoft.com
License: BSD
Keywords: ci,sip,b2bua,voip,rfc3261,sippy
Classifier: License :: OSI Approved :: BSD License
Classifier: Operating System :: POSIX
Classifier: Programming Language :: Python
License-File: LICENSE
